rfc3986-stubs/__init__.pyi
rfc3986-stubs/_mixin.pyi
rfc3986-stubs/api.pyi
rfc3986-stubs/builder.pyi
rfc3986-stubs/compat.pyi
rfc3986-stubs/exceptions.pyi
rfc3986-stubs/iri.pyi
rfc3986-stubs/misc.pyi
rfc3986-stubs/normalizers.pyi
rfc3986-stubs/parseresult.pyi
rfc3986-stubs/py.typed
rfc3986-stubs/uri.pyi
rfc3986-stubs/validators.pyi
rfc3986_stubs-2.0.0a4.dist-info/METADATA
rfc3986_stubs-2.0.0a4.dist-info/WHEEL
rfc3986_stubs-2.0.0a4.dist-info/top_level.txt
rfc3986_stubs-2.0.0a4.dist-info/RECORD
